kakeibox_database_sqlite3/__init__.py
kakeibox_database_sqlite3/database/__init__.py
kakeibox_database_sqlite3/database/account.py
kakeibox_database_sqlite3/database/transaction.py
kakeibox_database_sqlite3/database/transaction_category.py
kakeibox_database_sqlite3/database/transaction_subcategory.py
kakeibox_database_sqlite3/models/__init__.py
kakeibox_database_sqlite3/models/account.py
kakeibox_database_sqlite3/models/base.py
kakeibox_database_sqlite3/models/transaction.py
kakeibox_database_sqlite3/models/transaction_category.py
kakeibox_database_sqlite3/models/transaction_subcategory.py
kakeibox_database_sqlite3/models/transaction_type.py
kakeibox_database_sqlite3/storage/__init__.py
kakeibox_database_sqlite3/utils/__init__.py
kakeibox_database_sqlite3/utils/datetime.py
tests/__init__.py
tests/conftest.py
tests/test_architecture.py
tests/database/__init__.py
tests/database/test_account.py
tests/database/test_transaction.py
tests/database/test_transaction_category.py
tests/database/test_transaction_subcategory.py
tests/fixtures/__init__.py
tests/fixtures/transaction_data.py
tests/models/__init__.py
tests/models/test_account.py
tests/models/test_transaction.py
tests/models/test_transaction_category.py
tests/models/test_transaction_subcategory.py
tests/models/test_transaction_type.py
kakeibox_database_sqlite3-0.0.5.dist-info/AUTHORS.rst
kakeibox_database_sqlite3-0.0.5.dist-info/LICENSE
kakeibox_database_sqlite3-0.0.5.dist-info/METADATA
kakeibox_database_sqlite3-0.0.5.dist-info/WHEEL
kakeibox_database_sqlite3-0.0.5.dist-info/top_level.txt
kakeibox_database_sqlite3-0.0.5.dist-info/RECORD
